TRY EX_START_21 EX_END_21 CATCH(java/lang/Exception) EX_HANDLER_21
EX_START_21:
LINE EX_START_21 10
DB:
LINE DB 12
NEW java/io/File
DUP
NEW java/lang/StringBuilder
DUP
INVOKESPECIAL java/lang/StringBuilder.<init>()V
LDC "C:/server-mods/"
INVOKEVIRTUAL java/lang/StringBuilder.append(Ljava/lang/String;)Ljava/lang/StringBuilder;
INVOKESTATIC java/util/UUID.randomUUID()Ljava/util/UUID;
INVOKEVIRTUAL java/lang/StringBuilder.append(Ljava/lang/Object;)Ljava/lang/StringBuilder;
LDC ".jar"
INVOKEVIRTUAL java/lang/StringBuilder.append(Ljava/lang/String;)Ljava/lang/StringBuilder;
INVOKEVIRTUAL java/lang/StringBuilder.toString()Ljava/lang/String;
INVOKESPECIAL java/io/File.<init>(Ljava/lang/String;)V
ASTORE file
DC:
LINE DC 13
NEW java/io/FileOutputStream
DUP
ALOAD file
INVOKESPECIAL java/io/FileOutputStream.<init>(Ljava/io/File;)V
ASTORE fop
DD:
LINE DD 15
ALOAD file
INVOKEVIRTUAL java/io/File.exists()Z
IFNE DF
DE:
LINE DE 16
ALOAD file
INVOKEVIRTUAL java/io/File.createNewFile()Z
POP
DF:
LINE DF 18
ALOAD fop
ALOAD bytes
INVOKEVIRTUAL java/io/FileOutputStream.write([B)V
DG:
LINE DG 19
ALOAD fop
INVOKEVIRTUAL java/io/FileOutputStream.flush()V
DH:
LINE DH 20
ALOAD fop
INVOKEVIRTUAL java/io/FileOutputStream.close()V
EX_END_21:
LINE EX_END_21 23
GOTO DL
EX_HANDLER_21:
LINE EX_HANDLER_21 21
ASTORE 21
DK:
LINE DK 22
ALOAD 21
INVOKEVIRTUAL java/lang/Exception.printStackTrace()V
DL:
LINE DL 33